haskellian/__init__.py
haskellian/__init__.pyi
haskellian/asyn_iter/__init__.py
haskellian/asyn_iter/__init__.pyi
haskellian/asyn_iter/funcs.py
haskellian/asyn_iter/iter.py
haskellian/asyn_iter/lifting.py
haskellian/asyn_iter/managed.py
haskellian/asyn_iter/prefetching.py
haskellian/classes/__init__.py
haskellian/classes/__init__.pyi
haskellian/classes/applicative.py
haskellian/classes/functor.py
haskellian/classes/monad.py
haskellian/dicts/__init__.py
haskellian/dicts/__init__.pyi
haskellian/dicts/basics.py
haskellian/dicts/dict.py
haskellian/dicts/grouping.py
haskellian/dicts/lifting.py
haskellian/dicts/misc.py
haskellian/either/__init__.py
haskellian/either/__init__.pyi
haskellian/either/do_notation.py
haskellian/either/either.py
haskellian/either/funcs.py
haskellian/either/narrowing.py
haskellian/funcs/__init__.py
haskellian/funcs/__init__.pyi
haskellian/funcs/_flow.py
haskellian/funcs/_pipe.py
haskellian/iter/__init__.py
haskellian/iter/__init__.pyi
haskellian/iter/basics.py
haskellian/iter/batching.py
haskellian/iter/curried.py
haskellian/iter/indexing.py
haskellian/iter/iter.py
haskellian/iter/lifting.py
haskellian/iter/maps.py
haskellian/iter/misc.py
haskellian/iter/nested.py
haskellian/iter/searching.py
haskellian/iter/slicing.py
haskellian/iter/transposing.py
haskellian/iter/zipping.py
haskellian/kwargs/__init__.py
haskellian/kwargs/__init__.pyi
haskellian/kwargs/inspection.py
haskellian/kwargs/kwargs.py
haskellian/option/__init__.py
haskellian/option/__init__.pyi
haskellian/option/do_notation.py
haskellian/promise/__init__.py
haskellian/promise/__init__.pyi
haskellian/promise/funcs.py
haskellian/promise/lifting.py
haskellian/promise/managed.py
haskellian/promise/promise.py
haskellian/trees/__init__.py
haskellian/trees/__init__.pyi
haskellian/trees/trees.py
haskellian-0.5.14.dist-info/METADATA
haskellian-0.5.14.dist-info/WHEEL
haskellian-0.5.14.dist-info/top_level.txt
haskellian-0.5.14.dist-info/RECORD
