Metadata-Version: 2.4
Name: haskellian
Version: 0.5.14
Summary: The functional programming library you need
Author-email: Marcel Claramunt <marcel@moveread.com>
Project-URL: repo, https://github.com/moveread/haskellian.git
Requires-Python: >=3.10
Requires-Dist: lazy-loader
Requires-Dist: ramda
